LICENSE.md
README.md
setup.py
src/shadow/__init__.py
src/shadow/eaat.py
src/shadow/losses.py
src/shadow/module_wrapper.py
src/shadow/mt.py
src/shadow/pseudo.py
src/shadow/utils.py
src/shadow/vat.py
src/shadow_ssml.egg-info/PKG-INFO
src/shadow_ssml.egg-info/SOURCES.txt
src/shadow_ssml.egg-info/dependency_links.txt
src/shadow_ssml.egg-info/requires.txt
src/shadow_ssml.egg-info/top_level.txt