Metadata-Version: 2.1
Name: shadow-ssml
Version: 1.0.3
Summary: Semi-supervised machine learning for PyTorch.
Home-page: https://github.com/sandialabs/shadow
Author: Shadow Developers
Author-email: dzander@sandia.gov
Maintainer-email: dzander@sandia.gov
License: Revised BSD
Platform: UNKNOWN
Requires-Python: >=3.6
License-File: LICENSE.md
